odoo10_addon_hr_timesheet_task-10.0.1.0.3-nspkg.pth
odoo/addons/hr_timesheet_task/README.rst
odoo/addons/hr_timesheet_task/__init__.py
odoo/addons/hr_timesheet_task/__manifest__.py
odoo/addons/hr_timesheet_task/i18n/hr_timesheet_task.pot
odoo/addons/hr_timesheet_task/i18n/it.po
odoo/addons/hr_timesheet_task/static/description/icon.png
odoo/addons/hr_timesheet_task/static/src/css/timesheet.css
odoo/addons/hr_timesheet_task/static/src/js/timesheet.js
odoo/addons/hr_timesheet_task/static/src/xml/timesheet.xml
odoo/addons/hr_timesheet_task/views/hr_timesheet_assets.xml
odoo/addons/hr_timesheet_task/views/hr_timesheet_view.xml
odoo10_addon_hr_timesheet_task-10.0.1.0.3.dist-info/METADATA
odoo10_addon_hr_timesheet_task-10.0.1.0.3.dist-info/WHEEL
odoo10_addon_hr_timesheet_task-10.0.1.0.3.dist-info/namespace_packages.txt
odoo10_addon_hr_timesheet_task-10.0.1.0.3.dist-info/top_level.txt
odoo10_addon_hr_timesheet_task-10.0.1.0.3.dist-info/RECORD
