Metadata-Version: 2.1
Name: odoo10-addon-hr-timesheet-task
Version: 10.0.1.0.3
Summary: Allow the user to select task in a timesheet
Home-page: https://odoo-community.org/
Author: Scopea, Niboo, Camptocamp SA, Odoo Community Association (OCA)
Author-email: support@odoo-community.org
License: AGPL-3
Platform: UNKNOWN
Classifier: Programming Language :: Python
Classifier: Framework :: Odoo
Classifier: License :: OSI Approved :: GNU Affero General Public License v3
Requires-Python: ~=2.7
Requires-Dist: odoo (<10.1dev,>=10.0)
